setup.py
colored_debug_prints/__init__.py
colored_debug_prints/colored_prints.py
colored_debug_prints/print_utils.py
colored_debug_prints.egg-info/PKG-INFO
colored_debug_prints.egg-info/SOURCES.txt
colored_debug_prints.egg-info/dependency_links.txt
colored_debug_prints.egg-info/requires.txt
colored_debug_prints.egg-info/top_level.txt