Metadata-Version: 2.1
Name: colored-debug-prints
Version: 0.1.8
Summary: Simple colored debug prints
Author: Mistercoolertyper
Author-email: leonwagner09@gmail.com
Keywords: python,first package
Classifier: Development Status :: 3 - Alpha
Classifier: Intended Audience :: Education
Classifier: Programming Language :: Python :: 2
Classifier: Programming Language :: Python :: 3
Classifier: Operating System :: MacOS :: MacOS X
Classifier: Operating System :: Microsoft :: Windows
